pyhdfe/__init__.py
pyhdfe/algorithms.py
pyhdfe/interface.py
pyhdfe/utilities.py
pyhdfe/version.py
pyhdfe/tests/__init__.py
pyhdfe/tests/conftest.py
pyhdfe/tests/test_hdfe.py
pyhdfe-0.2.0.dist-info/LICENSE.txt
pyhdfe-0.2.0.dist-info/METADATA
pyhdfe-0.2.0.dist-info/WHEEL
pyhdfe-0.2.0.dist-info/top_level.txt
pyhdfe-0.2.0.dist-info/RECORD
