Metadata-Version: 2.1
Name: pyhdfe
Version: 0.2.0
Summary: High dimensional fixed effect absorption with Python 3
Home-page: https://github.com/jeffgortmaker/pyhdfe
Author: Jeff Gortmaker
Author-email: jeff@jeffgortmaker.com
License: MIT
Project-URL: Documentation, http://pyhdfe.readthedocs.io/en/latest
Project-URL: Tracker, https://github.com/jeffgortmaker/pyhdfe/issues
Platform: UNKNOWN
Classifier: Development Status :: 4 - Beta
Classifier: Intended Audience :: Science/Research
Classifier: License :: OSI Approved :: MIT License
Classifier: Operating System :: OS Independent
Classifier: Programming Language :: Python
Classifier: Programming Language :: Python :: 3
Classifier: Programming Language :: Python :: 3.6
Classifier: Programming Language :: Python :: 3.7
Classifier: Programming Language :: Python :: 3.8
Classifier: Programming Language :: Python :: 3.9
Classifier: Topic :: Scientific/Engineering
Requires-Python: >=3.6
Provides-Extra: tests
Provides-Extra: docs
License-File: LICENSE.txt
